{
  "date": "2026-07-10",
  "collector": {
    "ok": true,
    "at": "2026-07-10T02:00:05.827Z",
    "late": false,
    "counts": {
      "krungthai": 20,
      "krungsri": 16,
      "superrich": 20
    }
  },
  "push": {
    "ok": true,
    "at": "2026-07-10T02:03:10Z",
    "detail": "published"
  },
  "updated": "2026-07-10T02:05:05.092Z",
  "captures": {
    "kjourney": {
      "ok": true,
      "at": "2026-07-10T02:00:15.446Z",
      "count": 20
    },
    "mastercard": {
      "ok": true,
      "at": "2026-07-10T02:03:10.123Z",
      "count": 10
    }
  },
  "validation": {
    "ok": true,
    "at": "2026-07-10T02:05:05.091Z"
  }
}
